src/__init__.py
src/exificator.py
exificator-1.0.0.dist-info/LICENSE
exificator-1.0.0.dist-info/METADATA
exificator-1.0.0.dist-info/WHEEL
exificator-1.0.0.dist-info/entry_points.txt
exificator-1.0.0.dist-info/top_level.txt
exificator-1.0.0.dist-info/RECORD
