Metadata-Version: 2.1
Name: exificator
Version: 1.0.0
Summary: A command line application for modifying EXIF metadata in JPEG images.
Home-page: https://github.com/julianjm/exificator
Author: Julian J. M.
Author-email: julianjm@gmail.com
License: MIT
Keywords: exif jpeg image metadata xss payload
License-File: LICENSE
Requires-Dist: exif (>=1.6.0)
